k3num/__init__.py
k3num/hex.py
k3num/readable.py
k3num-0.1.10.dist-info/licenses/LICENSE
k3num-0.1.10.dist-info/METADATA
k3num-0.1.10.dist-info/WHEEL
k3num-0.1.10.dist-info/top_level.txt
k3num-0.1.10.dist-info/RECORD
